service_driver/__init__.py
service_driver/__main__.py
service_driver/_version.py
service_driver/command.py
service_driver/har_parser.py
service_driver/loader_swagger.py
service_driver/project_generator.py
service_driver/sd_utils.py
service_driver/swagger_generate.py
service_driver/tenplate.py
service_driver/testcase_mixin.py
service_driver/templates/api.tpl
service_driver/templates/api_demo.tpl
service_driver/templates/base_api.tpl
service_driver/templates/base_testcase.tpl
service_driver/templates/har2api_case.tpl
service_driver/templates/har2case.tpl
service_driver/templates/testcase_demo.tpl
service_driver/utils/__init__.py
service_driver/utils/custom_str_utils.py
service_driver/utils/database_conn.py
service_driver/utils/fake.py
service_driver/utils/placeholder.py
service_driver/utils/service_logger.py
service_driver-1.5.0.dist-info/LICENSE.txt
service_driver-1.5.0.dist-info/METADATA
service_driver-1.5.0.dist-info/WHEEL
service_driver-1.5.0.dist-info/entry_points.txt
service_driver-1.5.0.dist-info/top_level.txt
service_driver-1.5.0.dist-info/RECORD
