Metadata-Version: 2.1
Name: service-driver
Version: 1.5.0
Summary: api test framework cli
Home-page: https://github.com/JxcChen/service-driver
Author: CHNJX
Author-email: 360088940@qq.com
License: UNKNOWN
Platform: UNKNOWN
Requires-Dist: allure-pytest (==2.12.0)
Requires-Dist: allure-python-commons (==2.12.0)
Requires-Dist: attrs (==22.2.0)
Requires-Dist: bleach (==6.0.0)
Requires-Dist: certifi (==2022.12.7)
Requires-Dist: charset-normalizer (==3.0.1)
Requires-Dist: click (==8.1.3)
Requires-Dist: colorama (==0.4.6)
Requires-Dist: docutils (==0.19)
Requires-Dist: exceptiongroup (==1.1.0)
Requires-Dist: Faker (==16.6.1)
Requires-Dist: idna (==3.4)
Requires-Dist: importlib-metadata (==6.0.0)
Requires-Dist: iniconfig (==2.0.0)
Requires-Dist: jaraco.classes (==3.2.3)
Requires-Dist: Jinja2 (==3.1.2)
Requires-Dist: jsonpath (==0.82)
Requires-Dist: jsonschema (==4.17.3)
Requires-Dist: keyring (==23.13.1)
Requires-Dist: markdown-it-py (==2.1.0)
Requires-Dist: MarkupSafe (==2.1.2)
Requires-Dist: mdurl (==0.1.2)
Requires-Dist: more-itertools (==9.0.0)
Requires-Dist: packaging (==23.0)
Requires-Dist: pkginfo (==1.9.6)
Requires-Dist: pluggy (==1.0.0)
Requires-Dist: Pygments (==2.14.0)
Requires-Dist: PyMySQL (==1.0.2)
Requires-Dist: pyrsistent (==0.19.3)
Requires-Dist: pytest (==7.2.1)
Requires-Dist: python-dateutil (==2.8.2)
Requires-Dist: pywin32-ctypes (==0.2.0)
Requires-Dist: PyYAML (==6.0)
Requires-Dist: readme-renderer (==37.3)
Requires-Dist: requests (==2.28.2)
Requires-Dist: requests-toolbelt (==0.10.1)
Requires-Dist: rfc3986 (==2.0.0)
Requires-Dist: rich (==13.3.1)
Requires-Dist: six (==1.16.0)
Requires-Dist: tomli (==2.0.1)
Requires-Dist: twine (==4.0.2)
Requires-Dist: urllib3 (==1.26.14)
Requires-Dist: webencodings (==0.5.1)
Requires-Dist: zipp (==3.12.1)
